
[
    {
      "id": 1,
      "segment_name": "apartments",
      "estate_title": "Luxury Downtown Apartment",
      "description": "Modern apartment in the heart of the city with stunning views.",
      "price": "$2000/month",
      "status": "rent",
      "bed": "4",
      "bath": "2",
      "area": "1200 sq ft",
      "location": "Downtown, NewYork, USA",
      "image": "https://i.ibb.co/5xd2K55/id1.jpg",
      "facilities": ["Living room", "Swimming pool", "Gym"]
    },
    {
      "id": 2,
      "segment_name": "apartments",
      "estate_title": "Cozy Studio Apartment",
      "description": "Charming studio apartment with natural light and a cozy atmosphere.",
      "price": "$150000",
      "status": "sale",
      "bed": "4",
      "bath": "2",
      "area": "600 sq ft",
      "location": "Suburbia, California, USA",
      "image": "https://i.ibb.co/PZ2Vsd3/id2.jpg",
      "facilities": ["Living area", "Fitness center", "Laundry room"]
    },
    {
      "id": 3,
      "segment_name": "apartments",
      "estate_title": "Luxury Beachfront Condo",
      "description": "Spacious condo overlooking the ocean with resort-style amenities.",
      "price": "$5000/month",
      "status": "rent",
      "bed": "4",
      "bath": "2",
      "area": "1800 sq ft",
      "location": "Coastal Town, Florida, USA",
      "image": "https://i.ibb.co/G0Yx2cs/id3.jpg",
      "facilities": ["Ocean view balcony", "Poolside cabanas", "Fitness center"]
    },
    {
      "id": 4,
      "segment_name": "vacation rental",
      "estate_title": "Secluded Mountain Cabin",
      "description": "Escape to nature in this cozy cabin surrounded by forests and mountains.",
      "price": "$250/night",
      "status": "rent",
      "bed": "4",
      "bath": "2",
      "area": "1000 sq ft",
      "location": "Mountain Village, Colorado, USA",
      "image": "https://i.ibb.co/KhkCK1k/id4.jpg",
      "facilities": ["Fireplace", "Hiking trails", "Outdoor hot tub"]
    },
    {
      "id": 5,
      "segment_name": "vacation rental",
      "estate_title": "Beachfront Villa",
      "description": "Relax in luxury at this beachfront villa with private beach access.",
      "price": "$4000/week",
      "status": "rent",
      "bed": "4",
      "bath": "2",
      "area": "3000 sq ft",
      "location": "Coastal Resort, Hawaii, USA",
      "image": "https://i.ibb.co/3722wJ8/id5.jpg",
      "facilities": ["Private pool", "Beachfront terrace", "Outdoor BBQ area"]
    },
    {
      "id": 6,
      "segment_name": "single-family homes",
      "estate_title": "Spacious Family Home",
      "description": "Ideal family home with ample space for everyone, situated in a peaceful neighborhood.",
      "price": "$350000",
      "status": "sale",
      "bed": "4",
      "bath": "2",
      "area": "2500 sq ft",
      "location": "Suburban City, Texas, USA",
      "image": "https://i.ibb.co/VTq0Gc9/id6.jpg",
      "facilities": ["Large backyard", "Gourmet kitchen", "Home office"]
    },
    {
      "id": 7,
      "segment_name": "single-family homes",
      "estate_title": "Historic Colonial House",
      "description": "Charming colonial-style house with historic architecture and modern upgrades.",
      "price": "$2800/month",
      "status": "rent",
      "bed": "4",
      "bath": "2",
      "area": "2000 sq ft",
      "location": "Historic District, Massachusetts, USA",
      "image": "https://i.ibb.co/HK9H4sV/id7.jpg",
      "facilities": ["Wrap-around porch", "Garden courtyard", "Original hardwood floors"]
    },
    {
      "id": 8,
      "segment_name": "single-family homes",
      "estate_title": "Lakefront Retreat",
      "description": "Tranquil lakefront property offering breathtaking views and outdoor living spaces.",
      "price": "$600000",
      "status": "sale",
      "bed": "4",
      "bath": "2",
      "area": "3500 sq ft",
      "location": "Lakefront Community, Michigan, USA",
      "image": "https://i.ibb.co/wNKRRzz/id8.jpg",
      "facilities": ["Boat dock", "Lakefront deck", "Outdoor kitchen"]
    },
    {
      "id": 9,
      "segment_name": "single-family homes",
      "estate_title": "Rural Farmhouse",
      "description": "Quaint farmhouse nestled in the countryside with rustic charm and scenic views.",
      "price": "$1800/month",
      "status": "rent",
      "bed": "4",
      "bath": "2",
      "area": "1800 sq ft",
      "location": "Rural Village, Kansas, USA",
      "image": "https://i.ibb.co/Ht8jKFw/id9.jpg",
      "facilities": ["Wrap-around porch", "Barn", "Pasture"]
    }
  ]
  